autogllight/__init__.py
autogllight/hpo/__init__.py
autogllight/hpo/advisorbase.py
autogllight/hpo/anneal_advisorhpo.py
autogllight/hpo/auto_module.py
autogllight/hpo/autone.py
autogllight/hpo/base.py
autogllight/hpo/bayes_advisor.py
autogllight/hpo/bayes_advisorchoco.py
autogllight/hpo/cmaes_advisorchoco.py
autogllight/hpo/grid_advisor.py
autogllight/hpo/grid_advisorchoco.py
autogllight/hpo/mocmaes_advisorchoco.py
autogllight/hpo/quasi_advisorchoco.py
autogllight/hpo/rand_advisor.py
autogllight/hpo/rand_advisorchoco.py
autogllight/hpo/tpe_advisorhpo.py
autogllight/hpo/autone_file/__init__.py
autogllight/hpo/autone_file/utils.py
autogllight/hpo/suggestion/__init__.py
autogllight/hpo/suggestion/models.py
autogllight/hpo/suggestion/algorithm/__init__.py
autogllight/hpo/suggestion/algorithm/abstract_algorithm.py
autogllight/hpo/suggestion/algorithm/base_chocolate_algorithm.py
autogllight/hpo/suggestion/algorithm/base_hyperopt_algorithm.py
autogllight/hpo/suggestion/algorithm/base_skopt_algorithm.py
autogllight/hpo/suggestion/algorithm/bayesian_optimization.py
autogllight/hpo/suggestion/algorithm/chocolate_bayes.py
autogllight/hpo/suggestion/algorithm/chocolate_grid_search.py
autogllight/hpo/suggestion/algorithm/chocolate_random_search.py
autogllight/hpo/suggestion/algorithm/cmaes.py
autogllight/hpo/suggestion/algorithm/grid_search.py
autogllight/hpo/suggestion/algorithm/hyperopt_random_search.py
autogllight/hpo/suggestion/algorithm/mocmaes.py
autogllight/hpo/suggestion/algorithm/particle_swarm_optimization.py
autogllight/hpo/suggestion/algorithm/quasi_random_search.py
autogllight/hpo/suggestion/algorithm/random_search.py
autogllight/hpo/suggestion/algorithm/simulate_anneal.py
autogllight/hpo/suggestion/algorithm/skopt_bayesian_optimization.py
autogllight/hpo/suggestion/algorithm/tpe.py
autogllight/hpo/suggestion/algorithm/util.py
autogllight/hpo/suggestion/early_stop_algorithm/__init__.py
autogllight/hpo/suggestion/early_stop_algorithm/abstract_early_stop.py
autogllight-0.1.1.dist-info/METADATA
autogllight-0.1.1.dist-info/WHEEL
autogllight-0.1.1.dist-info/top_level.txt
autogllight-0.1.1.dist-info/RECORD
