Metadata-Version: 2.1
Name: autogllight
Version: 0.1.1
Summary: AutoML tools for graph-structure dataset
Author: THUMNLab/aglteam
Author-email: autogl@tsinghua.edu.cn
Maintainer: THUMNLab/aglteam
Classifier: Development Status :: 4 - Beta
Classifier: License :: OSI Approved :: Apache Software License
Classifier: Programming Language :: Python :: 3 :: Only
Classifier: Programming Language :: Python :: 3.6
Requires-Python: >=3.6
Requires-Dist: pyyaml
Requires-Dist: pytest
